pyrattle/__init__.py
pyrattle/errors.py
pyrattle/pyrattle.py
pyrattle-0.2.0.dist-info/LICENSE.md
pyrattle-0.2.0.dist-info/METADATA
pyrattle-0.2.0.dist-info/WHEEL
pyrattle-0.2.0.dist-info/RECORD
