Metadata-Version: 2.1
Name: pyrattle
Version: 0.2.0
Summary: Windows Defender wrapper
Author: Yassine DAMIRI
Author-email: yassine.damiri@epita.fr
Requires-Python: >=3.12,<4.0
Classifier: Programming Language :: Python :: 3
Classifier: Programming Language :: Python :: 3.12
